PySmartCard/CpuCard.py
PySmartCard/DCIC32.DLL
PySmartCard/Example.py
PySmartCard/ReaderLib.dll
PySmartCard/ReaderLib_64.dll
PySmartCard/__init__.py
PySmartCard/dcrf32.dll
PySmartCard/demo.py
PySmartCard/libReaderlib.so
PySmartCard/libReaderlib_64.so
PySmartCard/libpcsclite.so
PySmartCard/libpcsclite_64.so
PySmartCard/librf.so
PySmartCard-1.4.0.dist-info/METADATA
PySmartCard-1.4.0.dist-info/WHEEL
PySmartCard-1.4.0.dist-info/top_level.txt
PySmartCard-1.4.0.dist-info/RECORD
