Metadata-Version: 2.1
Name: PySmartCard
Version: 1.4.0
Summary: CPU card [non-logic encryption card] operation library, providing support for PCSC/D8/D6/T6 readers
Home-page: https://www.maybetodaystudio.com/blog/2018/11/25/python_smart_card/
Author: jaymi_k
Author-email: jinming_huang@foxmail.com
License: GPL
Keywords: smartcard,cpucard,pysmartcard,PySmartCard,pythonsmartcard,PythonSmartCard,reader,PCSC,D6,D8,T6,pyscard
Platform: UNKNOWN
Classifier: Development Status :: 3 - Alpha
Classifier: Intended Audience :: Developers
Classifier: Topic :: Software Development :: Libraries :: Application Frameworks
Classifier: License :: OSI Approved :: GNU General Public License (GPL)
Classifier: Programming Language :: Python :: 2
Classifier: Programming Language :: Python :: 2.5
Classifier: Programming Language :: Python :: 2.6
Classifier: Programming Language :: Python :: 2.7
Classifier: Programming Language :: Python :: 3
Classifier: Programming Language :: Python :: 3.3
Classifier: Programming Language :: Python :: 3.4
Classifier: Programming Language :: Python :: 3.5
Classifier: Programming Language :: Python :: 3.6
Classifier: Programming Language :: Python :: 3.7
